{"Capital Improvements":{"id":"Capital Improvements","description":"Roads, drainage, buildings, other infrastructure","budget_link":"","info_link":""},"Capital Improvements / City - Bonds":{"id":"Capital Improvements / City - Bonds","description":"Funded with debt ","budget_link":"","info_link":""},"Capital Improvements / City - Bonds / Drainage":{"id":"Capital Improvements / City - Bonds / Drainage","description":"","budget_link":"","info_link":""},"Capital Improvements / City - Bonds / Public Buildings":{"id":"Capital Improvements / City - Bonds / Public Buildings","description":"","budget_link":"","info_link":""},"Capital Improvements / City - Bonds / Recreation/Parks":{"id":"Capital Improvements / City - Bonds / Recreation/Parks","description":"","budget_link":"","info_link":""},"Capital Improvements / City - Bonds / Sidewalks":{"id":"Capital Improvements / City - Bonds / Sidewalks","description":"","budget_link":"","info_link":""},"Capital Improvements / City - Bonds / Streets":{"id":"Capital Improvements / City - Bonds / Streets","description":"","budget_link":"","info_link":""},"Capital Improvements / City - Cash":{"id":"Capital Improvements / City - Cash","description":"Paid with general fund revenue ","budget_link":"","info_link":""},"Capital Improvements / City - Cash / Administrative/Program Costs":{"id":"Capital Improvements / City - Cash / Administrative/Program Costs","description":"","budget_link":"","info_link":""},"Capital Improvements / City - Cash / Drainage":{"id":"Capital Improvements / City - Cash / Drainage","description":"","budget_link":"","info_link":""},"Capital Improvements / City - Cash / Normal Capital and Reserves":{"id":"Capital Improvements / City - Cash / Normal Capital and Reserves","description":"Accounted by department ","budget_link":"","info_link":""},"Capital Improvements / City - Cash / Public Buildings":{"id":"Capital Improvements / City - Cash / Public Buildings","description":"","budget_link":"","info_link":""},"Capital Improvements / City - Cash / Recreation/Parks":{"id":"Capital Improvements / City - Cash / Recreation/Parks","description":"","budget_link":"","info_link":""},"Capital Improvements / City - Cash / Sidewalks":{"id":"Capital Improvements / City - Cash / Sidewalks","description":"","budget_link":"","info_link":""},"Capital Improvements / City - Cash / Streets":{"id":"Capital Improvements / City - Cash / Streets","description":"","budget_link":"","info_link":""},"Capital Improvements / Parish - Cash":{"id":"Capital Improvements / Parish - Cash","description":"Paid with general fund revenue","budget_link":"","info_link":""},"Capital Improvements / Parish - Cash / Bridges":{"id":"Capital Improvements / Parish - Cash / Bridges","description":"","budget_link":"","info_link":""},"Capital Improvements / Parish - Cash / Drainage":{"id":"Capital Improvements / Parish - Cash / Drainage","description":"","budget_link":"","info_link":""},"Capital Improvements / Parish - Cash / Public Buildings":{"id":"Capital Improvements / Parish - Cash / Public Buildings","description":"","budget_link":"","info_link":""},"Capital Improvements / Parish - Cash / Widening/Realignment/Reconstruction":{"id":"Capital Improvements / Parish - Cash / Widening/Realignment/Reconstruction","description":"","budget_link":"","info_link":""},"Community":{"id":"Community","description":"Housing, Health, Social Services, Recreation, Culture ","budget_link":"","info_link":""},"Community / Health Unit":{"id":"Community / Health Unit","description":"Louisiana Dept. Health ","budget_link":"","info_link":""},"Community / Parks & Recreation":{"id":"Community / Parks & Recreation","description":"","budget_link":"","info_link":""},"Community / Parks & Recreation / Arts & Culture":{"id":"Community / Parks & Recreation / Arts & Culture","description":"","budget_link":"","info_link":""},"Community / Parks & Recreation / Athletic Programs":{"id":"Community / Parks & Recreation / Athletic Programs","description":"","budget_link":"","info_link":""},"Community / Parks & Recreation / Athletic Programs / Other Programs":{"id":"Community / Parks & Recreation / Athletic Programs / Other Programs","description":"","budget_link":"","info_link":""},"Community / Parks & Recreation / Athletic Programs / Swimming":{"id":"Community / Parks & Recreation / Athletic Programs / Swimming","description":"","budget_link":"","info_link":""},"Community / Parks & Recreation / Athletic Programs / Tennis":{"id":"Community / Parks & Recreation / Athletic Programs / Tennis","description":"","budget_link":"","info_link":""},"Community / Parks & Recreation / Athletic Programs / Therapeutic Recreation":{"id":"Community / Parks & Recreation / Athletic Programs / Therapeutic Recreation","description":"","budget_link":"","info_link":""},"Community / Parks & Recreation / Centers & Other Programs":{"id":"Community / Parks & Recreation / Centers & Other Programs","description":"","budget_link":"","info_link":""},"Community / Parks & Recreation / Director's Office":{"id":"Community / Parks & Recreation / Director's Office","description":"","budget_link":"","info_link":""},"Community / Parks & Recreation / Operations & Maintenance":{"id":"Community / Parks & Recreation / Operations & Maintenance","description":"","budget_link":"","info_link":""},"Utilities / LUS / Administration":{"id":"Utilities / LUS / Administration","description":"ILOT, interest, depreciation","budget_link":"","info_link":""},"Utilities / LUS / Power Production":{"id":"Utilities / LUS / Power Production","description":"Power purchases, transmission charges","budget_link":"https://thecurrentla.com/wp-content/uploads/lcg-proposed-2023-budget-by-dept-1.pdf#page=257","info_link":""}}